deutschland/Regionalatlas/__init__.py
deutschland/Regionalatlas/api/__init__.py
deutschland/Regionalatlas/api/default_api.py
deutschland/Regionalatlas/api_client.py
deutschland/Regionalatlas/apis/__init__.py
deutschland/Regionalatlas/configuration.py
deutschland/Regionalatlas/exceptions.py
deutschland/Regionalatlas/model/__init__.py
deutschland/Regionalatlas/model_utils.py
deutschland/Regionalatlas/models/__init__.py
deutschland/Regionalatlas/rest.py
de_regionalatlas-0.1.0.dist-info/METADATA
de_regionalatlas-0.1.0.dist-info/WHEEL
de_regionalatlas-0.1.0.dist-info/RECORD
